[
    {
        "id": 3938718,
        "topic_id": "CP_42018598",
        "parent_id": 0,
        "target_id": 0,
        "user_id": "12907647",
        "reply_user_id": "12907647",
        "content": "花了一整天做的，里面有些数学演算的；现在在上洛谷课。明天又要疯狂写作业了呜呜呜\n前三关引导关不难，相信你已经大概了解“纸中立方地球世界”了\n如果第三关不能在200秒内通过我还是劝退你吧，不聪明玩不了\n设计地图ing...",
        "likes": 2,
        "unlikes": 0,
        "replies": 1,
        "top": 1,
        "removed": 0,
        "links": null,
        "created_at": "2023-02-11 19:32:38",
        "comment_from": "topic",
        "username": "小轩",
        "user_avatar_path": "https://static1.xesimg.com/udc-o-user-avatar/20240907/TalzonWMSyKikgD5ZEDafJ9YyA_d75edba0b573c72c.png",
        "reply_username": "小轩",
        "emojis": [],
        "is_like": false,
        "is_unlike": false,
        "is_topic_author_like": false,
        "is_topic_author_reply": true,
        "can_delete": false,
        "can_top": false,
        "reply_list": {
            "hasMore": false,
            "total": 1,
            "data": [
                {
                    "id": 3938871,
                    "topic_id": "CP_42018598",
                    "parent_id": 3938718,
                    "target_id": 3938718,
                    "user_id": "12907647",
                    "reply_user_id": "12907647",
                    "content": "看代码就直接剧透了，如果想挑战一下就先别看代码",
                    "likes": 0,
                    "unlikes": 0,
                    "replies": 0,
                    "top": 0,
                    "removed": 0,
                    "links": null,
                    "created_at": "2023-02-11 19:54:17",
                    "comment_from": "topic",
                    "username": "小轩",
                    "user_avatar_path": "https://static1.xesimg.com/udc-o-user-avatar/20240907/TalzonWMSyKikgD5ZEDafJ9YyA_d75edba0b573c72c.png",
                    "reply_username": "小轩",
                    "emojis": [],
                    "is_like": false,
                    "is_unlike": false,
                    "is_topic_author_like": false,
                    "is_topic_author_reply": true,
                    "can_delete": false,
                    "can_top": false,
                    "user_profile": null
                }
            ]
        },
        "user_profile": null
    },
    {
        "id": 4155710,
        "topic_id": "CP_42018598",
        "parent_id": 0,
        "target_id": 0,
        "user_id": "41513165",
        "reply_user_id": "12907647",
        "content": "催更！催更！催更！催更！催更！催更！催更！催更！催更！催更！催更！催更！催更！催更！催更！催更！催更！催更！催更！催更！催更！催更！催更！催更！催更！催更！催更！催更！催更！催更！催更！催更！催更！催更！催更！催更！催更！催更！催更！催更！催更！催更！催更！催更！催更！催更！催更！催更！催更！催更！催更！催更！催更！催更！催更！催更！催更！催更！催更！催更！催更！催更！催更！催更！催更！催更！催更",
        "likes": 0,
        "unlikes": 0,
        "replies": 2,
        "top": 0,
        "removed": 0,
        "links": null,
        "created_at": "2023-06-03 08:14:57",
        "comment_from": "topic",
        "username": "林林",
        "user_avatar_path": "https://static1.xesimg.com/udc-o-user-avatar/20210819/TalzC6w0Kluji9q55BUm8C1gkA1161.jpg",
        "reply_username": "小轩",
        "emojis": [],
        "is_like": false,
        "is_unlike": false,
        "is_topic_author_like": false,
        "is_topic_author_reply": false,
        "can_delete": false,
        "can_top": false,
        "reply_list": {
            "hasMore": false,
            "total": 2,
            "data": [
                {
                    "id": 4156109,
                    "topic_id": "CP_42018598",
                    "parent_id": 4155710,
                    "target_id": 4155710,
                    "user_id": "12907647",
                    "reply_user_id": "41513165",
                    "content": "没看见我个签吗",
                    "likes": 0,
                    "unlikes": 0,
                    "replies": 0,
                    "top": 0,
                    "removed": 0,
                    "links": null,
                    "created_at": "2023-06-03 10:44:02",
                    "comment_from": "message",
                    "username": "小轩",
                    "user_avatar_path": "https://static1.xesimg.com/udc-o-user-avatar/20240907/TalzonWMSyKikgD5ZEDafJ9YyA_d75edba0b573c72c.png",
                    "reply_username": "林林",
                    "emojis": [],
                    "is_like": false,
                    "is_unlike": false,
                    "is_topic_author_like": false,
                    "is_topic_author_reply": true,
                    "can_delete": false,
                    "can_top": false,
                    "user_profile": null
                },
                {
                    "id": 4156182,
                    "topic_id": "CP_42018598",
                    "parent_id": 4155710,
                    "target_id": 4156109,
                    "user_id": "41513165",
                    "reply_user_id": "12907647",
                    "content": "《有空编程》",
                    "likes": 0,
                    "unlikes": 0,
                    "replies": 0,
                    "top": 0,
                    "removed": 0,
                    "links": null,
                    "created_at": "2023-06-03 10:49:08",
                    "comment_from": "message",
                    "username": "林林",
                    "user_avatar_path": "https://static1.xesimg.com/udc-o-user-avatar/20210819/TalzC6w0Kluji9q55BUm8C1gkA1161.jpg",
                    "reply_username": "小轩",
                    "emojis": [],
                    "is_like": false,
                    "is_unlike": false,
                    "is_topic_author_like": false,
                    "is_topic_author_reply": false,
                    "can_delete": false,
                    "can_top": false,
                    "user_profile": null
                }
            ]
        },
        "user_profile": null
    },
    {
        "id": 4155709,
        "topic_id": "CP_42018598",
        "parent_id": 0,
        "target_id": 0,
        "user_id": "41513165",
        "reply_user_id": "12907647",
        "content": "催更！催更！催更！催更！催更！催更！催更！催更！催更！催更！催更！催更！催更！催更！催更！催更！催更！催更！催更！催更！催更！催更！催更！催更！催更！催更！催更！催更！催更！催更！催更！催更！催更！催更！催更！催更！催更！催更！催更！催更！催更！催更！催更！催更！催更！催更！催更！催更！催更！催更！催更！催更！催更！催更！催更！催更！催更！催更！催更！催更！催更！催更！催更！催更！催更！催更！催更",
        "likes": 0,
        "unlikes": 0,
        "replies": 0,
        "top": 0,
        "removed": 0,
        "links": null,
        "created_at": "2023-06-03 08:14:57",
        "comment_from": "topic",
        "username": "林林",
        "user_avatar_path": "https://static1.xesimg.com/udc-o-user-avatar/20210819/TalzC6w0Kluji9q55BUm8C1gkA1161.jpg",
        "reply_username": "小轩",
        "emojis": [],
        "is_like": false,
        "is_unlike": false,
        "is_topic_author_like": false,
        "is_topic_author_reply": false,
        "can_delete": false,
        "can_top": false,
        "reply_list": {
            "hasMore": false,
            "total": 0,
            "data": []
        },
        "user_profile": null
    },
    {
        "id": 4102500,
        "topic_id": "CP_42018598",
        "parent_id": 0,
        "target_id": 0,
        "user_id": "29968040",
        "reply_user_id": "12907647",
        "content": "这个游戏有一个bug，就是在执行旋转函数rotate3d时，没有考虑全面\n如在rotate3d(&apos;left&apos;)（向右旋转）（不要问我向右是left，游戏人物向左走就是要把左面放到前面，自然就是向右旋转）时，只考虑改变前后左右四个面的位置，然而在现实中旋转立方体时，不止这四个面要动，它的上下面也分别要进行顺时针和逆时针旋转",
        "likes": 0,
        "unlikes": 0,
        "replies": 3,
        "top": 0,
        "removed": 0,
        "links": null,
        "created_at": "2023-05-01 09:59:10",
        "comment_from": "topic",
        "username": "黄羿杰",
        "user_avatar_path": "https://static0.xesimg.com/udc-o-user-avatar/20210410/TalzTGb2L3-6e1wkJImvuYvwEQ1154.jpg",
        "reply_username": "小轩",
        "emojis": [],
        "is_like": false,
        "is_unlike": false,
        "is_topic_author_like": false,
        "is_topic_author_reply": false,
        "can_delete": false,
        "can_top": false,
        "reply_list": {
            "hasMore": false,
            "total": 3,
            "data": [
                {
                    "id": 4103936,
                    "topic_id": "CP_42018598",
                    "parent_id": 4102500,
                    "target_id": 4102500,
                    "user_id": "12907647",
                    "reply_user_id": "29968040",
                    "content": "哦，天。我本来就是旋转一圈，而不是整个正方体。",
                    "likes": 0,
                    "unlikes": 0,
                    "replies": 0,
                    "top": 0,
                    "removed": 0,
                    "links": null,
                    "created_at": "2023-05-02 10:31:35",
                    "comment_from": "message",
                    "username": "小轩",
                    "user_avatar_path": "https://static1.xesimg.com/udc-o-user-avatar/20240907/TalzonWMSyKikgD5ZEDafJ9YyA_d75edba0b573c72c.png",
                    "reply_username": "黄羿杰",
                    "emojis": [],
                    "is_like": false,
                    "is_unlike": false,
                    "is_topic_author_like": false,
                    "is_topic_author_reply": true,
                    "can_delete": false,
                    "can_top": false,
                    "user_profile": null
                },
                {
                    "id": 4107353,
                    "topic_id": "CP_42018598",
                    "parent_id": 4102500,
                    "target_id": 4103936,
                    "user_id": "29968040",
                    "reply_user_id": "12907647",
                    "content": "你看一下这个，我把你的修改了亿下，同时改正了你的rotate3d\nhttps://code.xueersi.com/home/project/detail?lang=code&pid=43910340&version=offline&form=python&langType=python",
                    "likes": 0,
                    "unlikes": 0,
                    "replies": 0,
                    "top": 0,
                    "removed": 0,
                    "links": [
                        {
                            "link": "https://code.xueersi.com/home/project/detail?lang=code&pid=43910340&version=offline&form=python&langType=python",
                            "text": "纸中立方"
                        }
                    ],
                    "created_at": "2023-05-03 13:13:37",
                    "comment_from": "topic",
                    "username": "黄羿杰",
                    "user_avatar_path": "https://static0.xesimg.com/udc-o-user-avatar/20210410/TalzTGb2L3-6e1wkJImvuYvwEQ1154.jpg",
                    "reply_username": "小轩",
                    "emojis": [],
                    "is_like": false,
                    "is_unlike": false,
                    "is_topic_author_like": false,
                    "is_topic_author_reply": false,
                    "can_delete": false,
                    "can_top": false,
                    "user_profile": null
                },
                {
                    "id": 5508153,
                    "topic_id": "CP_42018598",
                    "parent_id": 4102500,
                    "target_id": 4107353,
                    "user_id": "79932748",
                    "reply_user_id": "29968040",
                    "content": "《小轩和黄羿杰建立友谊的初见端倪》",
                    "likes": 2,
                    "unlikes": 0,
                    "replies": 0,
                    "top": 0,
                    "removed": 0,
                    "links": null,
                    "created_at": "2024-08-15 19:22:12",
                    "comment_from": "topic",
                    "username": "实变函数",
                    "user_avatar_path": "https://static0.xesimg.com/udc-o-user-avatar/20240219/Talzd7_uMAZmfn2jyKhnnEIn6Q1480.png",
                    "reply_username": "黄羿杰",
                    "emojis": [],
                    "is_like": false,
                    "is_unlike": false,
                    "is_topic_author_like": false,
                    "is_topic_author_reply": false,
                    "can_delete": false,
                    "can_top": false,
                    "user_profile": null
                }
            ]
        },
        "user_profile": null
    },
    {
        "id": 4018639,
        "topic_id": "CP_42018598",
        "parent_id": 0,
        "target_id": 0,
        "user_id": "2731368",
        "reply_user_id": "12907647",
        "content": "《颓废的作品于摆烂的你》《颓废的作品于摆烂的你》《颓废的作品于摆烂的你》《颓废的作品于摆烂的你》《颓废的作品于摆烂的你》《颓废的作品于摆烂的你》《颓废的作品于摆烂的你》《颓废的作品于摆烂的你》《颓废的作品于摆烂的你》《颓废的作品于摆烂的你》《颓废的作品于摆烂的你》《颓废的作品于摆烂的你》《颓废的作品于摆烂的你》《颓废的作品于摆烂的你》《颓废的作品于摆烂的你》《颓废的作品于摆烂的你》《颓废的作品于摆",
        "likes": 0,
        "unlikes": 0,
        "replies": 0,
        "top": 0,
        "removed": 0,
        "links": null,
        "created_at": "2023-03-18 20:07:17",
        "comment_from": "topic",
        "username": "林林",
        "user_avatar_path": "https://static0.xesimg.com/udc-o-user-avatar/20230527/Talzq9KIOaaUJKTgzzjag4l70w1251.png",
        "reply_username": "小轩",
        "emojis": [],
        "is_like": false,
        "is_unlike": false,
        "is_topic_author_like": false,
        "is_topic_author_reply": false,
        "can_delete": false,
        "can_top": false,
        "reply_list": {
            "hasMore": false,
            "total": 0,
            "data": []
        },
        "user_profile": null
    },
    {
        "id": 4018628,
        "topic_id": "CP_42018598",
        "parent_id": 0,
        "target_id": 0,
        "user_id": "2731368",
        "reply_user_id": "12907647",
        "content": "《颓废的作品于摆烂的你》《颓废的作品于摆烂的你》《颓废的作品于摆烂的你》《颓废的作品于摆烂的你》《颓废的作品于摆烂的你》《颓废的作品于摆烂的你》《颓废的作品于摆烂的你》《颓废的作品于摆烂的你》《颓废的作品于摆烂的你》《颓废的作品于摆烂的你》《颓废的作品于摆烂的你》《颓废的作品于摆烂的你》《颓废的作品于摆烂的你》《颓废的作品于摆烂的你》《颓废的作品于摆烂的你》《颓废的作品于摆烂的你》《颓废的作品于摆",
        "likes": 0,
        "unlikes": 0,
        "replies": 0,
        "top": 0,
        "removed": 0,
        "links": null,
        "created_at": "2023-03-18 20:06:13",
        "comment_from": "topic",
        "username": "林林",
        "user_avatar_path": "https://static0.xesimg.com/udc-o-user-avatar/20230527/Talzq9KIOaaUJKTgzzjag4l70w1251.png",
        "reply_username": "小轩",
        "emojis": [],
        "is_like": false,
        "is_unlike": false,
        "is_topic_author_like": false,
        "is_topic_author_reply": false,
        "can_delete": false,
        "can_top": false,
        "reply_list": {
            "hasMore": false,
            "total": 0,
            "data": []
        },
        "user_profile": null
    },
    {
        "id": 3950962,
        "topic_id": "CP_42018598",
        "parent_id": 0,
        "target_id": 0,
        "user_id": "9233272",
        "reply_user_id": "12907647",
        "content": "PyCharm一堆红色的错误警告还能运行，牛13",
        "likes": 0,
        "unlikes": 0,
        "replies": 0,
        "top": 0,
        "removed": 0,
        "links": null,
        "created_at": "2023-02-17 20:23:25",
        "comment_from": "topic",
        "username": "吴边吴际",
        "user_avatar_path": "https://t.100tal.com/avatar/%E5%90%B4%E8%BE%B9%E5%90%B4%E9%99%85",
        "reply_username": "小轩",
        "emojis": [],
        "is_like": false,
        "is_unlike": false,
        "is_topic_author_like": false,
        "is_topic_author_reply": false,
        "can_delete": false,
        "can_top": false,
        "reply_list": {
            "hasMore": false,
            "total": 0,
            "data": []
        },
        "user_profile": null
    },
    {
        "id": 3950727,
        "topic_id": "CP_42018598",
        "parent_id": 0,
        "target_id": 0,
        "user_id": "9233272",
        "reply_user_id": "12907647",
        "content": "运行后没有东西",
        "likes": 0,
        "unlikes": 0,
        "replies": 0,
        "top": 0,
        "removed": 0,
        "links": null,
        "created_at": "2023-02-17 19:44:35",
        "comment_from": "topic",
        "username": "吴边吴际",
        "user_avatar_path": "https://t.100tal.com/avatar/%E5%90%B4%E8%BE%B9%E5%90%B4%E9%99%85",
        "reply_username": "小轩",
        "emojis": [],
        "is_like": false,
        "is_unlike": false,
        "is_topic_author_like": false,
        "is_topic_author_reply": false,
        "can_delete": false,
        "can_top": false,
        "reply_list": {
            "hasMore": false,
            "total": 0,
            "data": []
        },
        "user_profile": null
    },
    {
        "id": 3942243,
        "topic_id": "CP_42018598",
        "parent_id": 0,
        "target_id": 0,
        "user_id": "41740320",
        "reply_user_id": "12907647",
        "content": "n.py&quot;, line 79, in move\n    self.x = len(self.data&#91;&apos;front&apos;&#93;&#91;self.y&#93;) - 1\nIndexError: list index out of range",
        "likes": 0,
        "unlikes": 0,
        "replies": 0,
        "top": 0,
        "removed": 0,
        "links": null,
        "created_at": "2023-02-12 19:16:13",
        "comment_from": "topic",
        "username": "满愿",
        "user_avatar_path": "https://static0.xesimg.com/udc-o-user-avatar/20240907/TalzRKYAtfLPAfEqXF1Fej_Ryw_f29627c0071b0e43.jpg",
        "reply_username": "小轩",
        "emojis": [],
        "is_like": false,
        "is_unlike": false,
        "is_topic_author_like": false,
        "is_topic_author_reply": false,
        "can_delete": false,
        "can_top": false,
        "reply_list": {
            "hasMore": false,
            "total": 0,
            "data": []
        },
        "user_profile": null
    },
    {
        "id": 3942238,
        "topic_id": "CP_42018598",
        "parent_id": 0,
        "target_id": 0,
        "user_id": "41740320",
        "reply_user_id": "12907647",
        "content": "Traceback (most recent call last):\n  File &quot;C:\\Users\\zh&apos;y\\学而思直播\\code\\cache\\asset\\42018598/main.py&quot;, line 146, in &lt;module&gt;\n    cube.move(&apos;left&apos;)\n  File &quot;C:\\Users\\zh&apos;y\\学而思直播\\code\\cache\\asset\\42018598/mai",
        "likes": 0,
        "unlikes": 0,
        "replies": 0,
        "top": 0,
        "removed": 0,
        "links": null,
        "created_at": "2023-02-12 19:15:37",
        "comment_from": "topic",
        "username": "满愿",
        "user_avatar_path": "https://static0.xesimg.com/udc-o-user-avatar/20240907/TalzRKYAtfLPAfEqXF1Fej_Ryw_f29627c0071b0e43.jpg",
        "reply_username": "小轩",
        "emojis": [],
        "is_like": false,
        "is_unlike": false,
        "is_topic_author_like": false,
        "is_topic_author_reply": false,
        "can_delete": false,
        "can_top": false,
        "reply_list": {
            "hasMore": false,
            "total": 0,
            "data": []
        },
        "user_profile": null
    },
    {
        "id": 3941935,
        "topic_id": "CP_42018598",
        "parent_id": 0,
        "target_id": 0,
        "user_id": "17870274",
        "reply_user_id": "12907647",
        "content": "按下↓然后一直→就轻松过关了？",
        "likes": 0,
        "unlikes": 0,
        "replies": 0,
        "top": 0,
        "removed": 0,
        "links": null,
        "created_at": "2023-02-12 18:20:04",
        "comment_from": "topic",
        "username": "王一帆",
        "user_avatar_path": "https://t.100tal.com/avatar/%E7%8E%8B%E4%B8%80%E5%B8%86",
        "reply_username": "小轩",
        "emojis": [],
        "is_like": false,
        "is_unlike": false,
        "is_topic_author_like": false,
        "is_topic_author_reply": false,
        "can_delete": false,
        "can_top": false,
        "reply_list": {
            "hasMore": false,
            "total": 0,
            "data": []
        },
        "user_profile": null
    },
    {
        "id": 3941098,
        "topic_id": "CP_42018598",
        "parent_id": 0,
        "target_id": 0,
        "user_id": "17870274",
        "reply_user_id": "12907647",
        "content": "1.22\n2.66?",
        "likes": 0,
        "unlikes": 0,
        "replies": 0,
        "top": 0,
        "removed": 0,
        "links": null,
        "created_at": "2023-02-12 14:55:33",
        "comment_from": "topic",
        "username": "王一帆",
        "user_avatar_path": "https://t.100tal.com/avatar/%E7%8E%8B%E4%B8%80%E5%B8%86",
        "reply_username": "小轩",
        "emojis": [],
        "is_like": false,
        "is_unlike": false,
        "is_topic_author_like": false,
        "is_topic_author_reply": false,
        "can_delete": false,
        "can_top": false,
        "reply_list": {
            "hasMore": false,
            "total": 0,
            "data": []
        },
        "user_profile": null
    },
    {
        "id": 3940330,
        "topic_id": "CP_42018598",
        "parent_id": 0,
        "target_id": 0,
        "user_id": "23588936",
        "reply_user_id": "12907647",
        "content": "“10秒过关”",
        "likes": 0,
        "unlikes": 0,
        "replies": 0,
        "top": 0,
        "removed": 0,
        "links": null,
        "created_at": "2023-02-12 11:24:36",
        "comment_from": "topic",
        "username": "vivi晴",
        "user_avatar_path": "https://static0.xesimg.com/udc-o-user-avatar/20231105/TalzkBCmRSMXb5krr9KvDGkkQg1628.jpeg",
        "reply_username": "小轩",
        "emojis": [],
        "is_like": false,
        "is_unlike": false,
        "is_topic_author_like": false,
        "is_topic_author_reply": false,
        "can_delete": false,
        "can_top": false,
        "reply_list": {
            "hasMore": false,
            "total": 0,
            "data": []
        },
        "user_profile": null
    },
    {
        "id": 3940019,
        "topic_id": "CP_42018598",
        "parent_id": 0,
        "target_id": 0,
        "user_id": "3846998",
        "reply_user_id": "12907647",
        "content": "乱点之后我竟然直接通关了！",
        "likes": 0,
        "unlikes": 0,
        "replies": 0,
        "top": 0,
        "removed": 0,
        "links": null,
        "created_at": "2023-02-12 10:12:46",
        "comment_from": "topic",
        "username": "付开霁",
        "user_avatar_path": "https://t.100tal.com/avatar/%E4%BB%98%E5%BC%80%E9%9C%81",
        "reply_username": "小轩",
        "emojis": [],
        "is_like": false,
        "is_unlike": false,
        "is_topic_author_like": false,
        "is_topic_author_reply": false,
        "can_delete": false,
        "can_top": false,
        "reply_list": {
            "hasMore": false,
            "total": 0,
            "data": []
        },
        "user_profile": null
    },
    {
        "id": 3940002,
        "topic_id": "CP_42018598",
        "parent_id": 0,
        "target_id": 0,
        "user_id": "3846998",
        "reply_user_id": "12907647",
        "content": "一通乱点之后报错了……",
        "likes": 0,
        "unlikes": 0,
        "replies": 0,
        "top": 0,
        "removed": 0,
        "links": null,
        "created_at": "2023-02-12 10:07:42",
        "comment_from": "topic",
        "username": "付开霁",
        "user_avatar_path": "https://t.100tal.com/avatar/%E4%BB%98%E5%BC%80%E9%9C%81",
        "reply_username": "小轩",
        "emojis": [],
        "is_like": false,
        "is_unlike": false,
        "is_topic_author_like": false,
        "is_topic_author_reply": false,
        "can_delete": false,
        "can_top": false,
        "reply_list": {
            "hasMore": false,
            "total": 0,
            "data": []
        },
        "user_profile": null
    },
    {
        "id": 3939997,
        "topic_id": "CP_42018598",
        "parent_id": 0,
        "target_id": 0,
        "user_id": "3846998",
        "reply_user_id": "12907647",
        "content": "vscode表示：第179行的cude打错了",
        "likes": 0,
        "unlikes": 0,
        "replies": 1,
        "top": 0,
        "removed": 0,
        "links": null,
        "created_at": "2023-02-12 10:05:13",
        "comment_from": "topic",
        "username": "付开霁",
        "user_avatar_path": "https://t.100tal.com/avatar/%E4%BB%98%E5%BC%80%E9%9C%81",
        "reply_username": "小轩",
        "emojis": [],
        "is_like": false,
        "is_unlike": false,
        "is_topic_author_like": false,
        "is_topic_author_reply": false,
        "can_delete": false,
        "can_top": false,
        "reply_list": {
            "hasMore": false,
            "total": 1,
            "data": [
                {
                    "id": 3939999,
                    "topic_id": "CP_42018598",
                    "parent_id": 3939997,
                    "target_id": 3939997,
                    "user_id": "3846998",
                    "reply_user_id": "3846998",
                    "content": "是cube吗",
                    "likes": 0,
                    "unlikes": 0,
                    "replies": 0,
                    "top": 0,
                    "removed": 0,
                    "links": null,
                    "created_at": "2023-02-12 10:05:45",
                    "comment_from": "topic",
                    "username": "付开霁",
                    "user_avatar_path": "https://t.100tal.com/avatar/%E4%BB%98%E5%BC%80%E9%9C%81",
                    "reply_username": "付开霁",
                    "emojis": [],
                    "is_like": false,
                    "is_unlike": false,
                    "is_topic_author_like": false,
                    "is_topic_author_reply": false,
                    "can_delete": false,
                    "can_top": false,
                    "user_profile": null
                }
            ]
        },
        "user_profile": null
    },
    {
        "id": 3939452,
        "topic_id": "CP_42018598",
        "parent_id": 0,
        "target_id": 0,
        "user_id": "11909587",
        "reply_user_id": "12907647",
        "content": "带有数字的地是啥意思，没懂用来干嘛\n这个引导太不友好了吧\n信息给的太少，反正我完全推理不出来",
        "likes": 0,
        "unlikes": 0,
        "replies": 1,
        "top": 0,
        "removed": 0,
        "links": null,
        "created_at": "2023-02-11 21:37:03",
        "comment_from": "topic",
        "username": "严子昱",
        "user_avatar_path": "https://static1.xesimg.com/udc-o-user-avatar/20210205/TalzLSX0iLBo-yUTsOT5pW95TA1420.jpg",
        "reply_username": "小轩",
        "emojis": [],
        "is_like": false,
        "is_unlike": false,
        "is_topic_author_like": false,
        "is_topic_author_reply": false,
        "can_delete": false,
        "can_top": false,
        "reply_list": {
            "hasMore": false,
            "total": 1,
            "data": [
                {
                    "id": 3939624,
                    "topic_id": "CP_42018598",
                    "parent_id": 3939452,
                    "target_id": 3939452,
                    "user_id": "12907647",
                    "reply_user_id": "11909587",
                    "content": "对，要玩下去才能推理",
                    "likes": 0,
                    "unlikes": 0,
                    "replies": 0,
                    "top": 0,
                    "removed": 0,
                    "links": null,
                    "created_at": "2023-02-11 22:25:31",
                    "comment_from": "message",
                    "username": "小轩",
                    "user_avatar_path": "https://static1.xesimg.com/udc-o-user-avatar/20240907/TalzonWMSyKikgD5ZEDafJ9YyA_d75edba0b573c72c.png",
                    "reply_username": "严子昱",
                    "emojis": [],
                    "is_like": false,
                    "is_unlike": false,
                    "is_topic_author_like": false,
                    "is_topic_author_reply": true,
                    "can_delete": false,
                    "can_top": false,
                    "user_profile": null
                }
            ]
        },
        "user_profile": null
    },
    {
        "id": 3939431,
        "topic_id": "CP_42018598",
        "parent_id": 0,
        "target_id": 0,
        "user_id": "11909587",
        "reply_user_id": "12907647",
        "content": "怪谈？\n小建议：按T显示提示（就是开头那些东西",
        "likes": 0,
        "unlikes": 0,
        "replies": 1,
        "top": 0,
        "removed": 0,
        "links": null,
        "created_at": "2023-02-11 21:33:41",
        "comment_from": "topic",
        "username": "严子昱",
        "user_avatar_path": "https://static1.xesimg.com/udc-o-user-avatar/20210205/TalzLSX0iLBo-yUTsOT5pW95TA1420.jpg",
        "reply_username": "小轩",
        "emojis": [],
        "is_like": false,
        "is_unlike": false,
        "is_topic_author_like": false,
        "is_topic_author_reply": false,
        "can_delete": false,
        "can_top": false,
        "reply_list": {
            "hasMore": false,
            "total": 1,
            "data": [
                {
                    "id": 3939620,
                    "topic_id": "CP_42018598",
                    "parent_id": 3939431,
                    "target_id": 3939431,
                    "user_id": "12907647",
                    "reply_user_id": "11909587",
                    "content": "不算怪谈\n呃，开头的提示我下次修剪",
                    "likes": 0,
                    "unlikes": 0,
                    "replies": 0,
                    "top": 0,
                    "removed": 0,
                    "links": null,
                    "created_at": "2023-02-11 22:24:01",
                    "comment_from": "message",
                    "username": "小轩",
                    "user_avatar_path": "https://static1.xesimg.com/udc-o-user-avatar/20240907/TalzonWMSyKikgD5ZEDafJ9YyA_d75edba0b573c72c.png",
                    "reply_username": "严子昱",
                    "emojis": [],
                    "is_like": false,
                    "is_unlike": false,
                    "is_topic_author_like": false,
                    "is_topic_author_reply": true,
                    "can_delete": false,
                    "can_top": false,
                    "user_profile": null
                }
            ]
        },
        "user_profile": null
    },
    {
        "id": 3939253,
        "topic_id": "CP_42018598",
        "parent_id": 0,
        "target_id": 0,
        "user_id": "3940552",
        "reply_user_id": "12907647",
        "content": "《list index out of range》\n用着用着就超限了",
        "likes": 0,
        "unlikes": 0,
        "replies": 3,
        "top": 0,
        "removed": 0,
        "links": null,
        "created_at": "2023-02-11 20:59:13",
        "comment_from": "topic",
        "username": "宋佳豪",
        "user_avatar_path": "https://static0.xesimg.com/udc-o-user-avatar/20230405/TalztnwqUsqosRlftupeOy3WZQ1756.png",
        "reply_username": "小轩",
        "emojis": [],
        "is_like": false,
        "is_unlike": false,
        "is_topic_author_like": false,
        "is_topic_author_reply": false,
        "can_delete": false,
        "can_top": false,
        "reply_list": {
            "hasMore": false,
            "total": 3,
            "data": [
                {
                    "id": 3939282,
                    "topic_id": "CP_42018598",
                    "parent_id": 3939253,
                    "target_id": 3939253,
                    "user_id": "12907647",
                    "reply_user_id": "3940552",
                    "content": "我也刚发现，很小概率碰到的，将在新版解决",
                    "likes": 0,
                    "unlikes": 0,
                    "replies": 0,
                    "top": 0,
                    "removed": 0,
                    "links": null,
                    "created_at": "2023-02-11 21:06:19",
                    "comment_from": "topic",
                    "username": "小轩",
                    "user_avatar_path": "https://static1.xesimg.com/udc-o-user-avatar/20240907/TalzonWMSyKikgD5ZEDafJ9YyA_d75edba0b573c72c.png",
                    "reply_username": "宋佳豪",
                    "emojis": [],
                    "is_like": false,
                    "is_unlike": false,
                    "is_topic_author_like": false,
                    "is_topic_author_reply": true,
                    "can_delete": false,
                    "can_top": false,
                    "user_profile": null
                },
                {
                    "id": 3939347,
                    "topic_id": "CP_42018598",
                    "parent_id": 3939253,
                    "target_id": 3939282,
                    "user_id": "3940552",
                    "reply_user_id": "12907647",
                    "content": "OK啦，通关了",
                    "likes": 0,
                    "unlikes": 0,
                    "replies": 0,
                    "top": 0,
                    "removed": 0,
                    "links": null,
                    "created_at": "2023-02-11 21:19:06",
                    "comment_from": "message",
                    "username": "宋佳豪",
                    "user_avatar_path": "https://static0.xesimg.com/udc-o-user-avatar/20230405/TalztnwqUsqosRlftupeOy3WZQ1756.png",
                    "reply_username": "小轩",
                    "emojis": [],
                    "is_like": false,
                    "is_unlike": false,
                    "is_topic_author_like": false,
                    "is_topic_author_reply": false,
                    "can_delete": false,
                    "can_top": false,
                    "user_profile": null
                },
                {
                    "id": 4102698,
                    "topic_id": "CP_42018598",
                    "parent_id": 3939253,
                    "target_id": 3939282,
                    "user_id": "29968040",
                    "reply_user_id": "12907647",
                    "content": "这应该不是小概率，而是算法问题，是rotate3d旋转算法有误导致",
                    "likes": 0,
                    "unlikes": 0,
                    "replies": 0,
                    "top": 0,
                    "removed": 0,
                    "links": null,
                    "created_at": "2023-05-01 12:43:46",
                    "comment_from": "topic",
                    "username": "黄羿杰",
                    "user_avatar_path": "https://static0.xesimg.com/udc-o-user-avatar/20210410/TalzTGb2L3-6e1wkJImvuYvwEQ1154.jpg",
                    "reply_username": "小轩",
                    "emojis": [],
                    "is_like": false,
                    "is_unlike": false,
                    "is_topic_author_like": false,
                    "is_topic_author_reply": false,
                    "can_delete": false,
                    "can_top": false,
                    "user_profile": null
                }
            ]
        },
        "user_profile": null
    },
    {
        "id": 3938849,
        "topic_id": "CP_42018598",
        "parent_id": 0,
        "target_id": 0,
        "user_id": "2731368",
        "reply_user_id": "12907647",
        "content": "很好，虽然通过了但是懵了",
        "likes": 0,
        "unlikes": 0,
        "replies": 3,
        "top": 0,
        "removed": 0,
        "links": null,
        "created_at": "2023-02-11 19:51:42",
        "comment_from": "topic",
        "username": "林林",
        "user_avatar_path": "https://static0.xesimg.com/udc-o-user-avatar/20230527/Talzq9KIOaaUJKTgzzjag4l70w1251.png",
        "reply_username": "小轩",
        "emojis": [],
        "is_like": false,
        "is_unlike": false,
        "is_topic_author_like": false,
        "is_topic_author_reply": false,
        "can_delete": false,
        "can_top": false,
        "reply_list": {
            "hasMore": false,
            "total": 3,
            "data": [
                {
                    "id": 3938867,
                    "topic_id": "CP_42018598",
                    "parent_id": 3938849,
                    "target_id": 3938849,
                    "user_id": "12907647",
                    "reply_user_id": "2731368",
                    "content": "可以看看代码试试，否则等我出正式版直接逝世",
                    "likes": 0,
                    "unlikes": 0,
                    "replies": 0,
                    "top": 0,
                    "removed": 0,
                    "links": null,
                    "created_at": "2023-02-11 19:53:45",
                    "comment_from": "topic",
                    "username": "小轩",
                    "user_avatar_path": "https://static1.xesimg.com/udc-o-user-avatar/20240907/TalzonWMSyKikgD5ZEDafJ9YyA_d75edba0b573c72c.png",
                    "reply_username": "林林",
                    "emojis": [],
                    "is_like": false,
                    "is_unlike": false,
                    "is_topic_author_like": false,
                    "is_topic_author_reply": true,
                    "can_delete": false,
                    "can_top": false,
                    "user_profile": null
                },
                {
                    "id": 3939298,
                    "topic_id": "CP_42018598",
                    "parent_id": 3938849,
                    "target_id": 3938849,
                    "user_id": "12907647",
                    "reply_user_id": "2731368",
                    "content": "我内部做了第三关，按↑→非常慢过，还只是一个3x3x3的cube啊\n（第三关开始有了两个传送门）",
                    "likes": 0,
                    "unlikes": 0,
                    "replies": 0,
                    "top": 0,
                    "removed": 0,
                    "links": null,
                    "created_at": "2023-02-11 21:08:47",
                    "comment_from": "topic",
                    "username": "小轩",
                    "user_avatar_path": "https://static1.xesimg.com/udc-o-user-avatar/20240907/TalzonWMSyKikgD5ZEDafJ9YyA_d75edba0b573c72c.png",
                    "reply_username": "林林",
                    "emojis": [],
                    "is_like": false,
                    "is_unlike": false,
                    "is_topic_author_like": false,
                    "is_topic_author_reply": true,
                    "can_delete": false,
                    "can_top": false,
                    "user_profile": null
                },
                {
                    "id": 3939370,
                    "topic_id": "CP_42018598",
                    "parent_id": 3938849,
                    "target_id": 3939298,
                    "user_id": "2731368",
                    "reply_user_id": "12907647",
                    "content": "o",
                    "likes": 0,
                    "unlikes": 0,
                    "replies": 0,
                    "top": 0,
                    "removed": 0,
                    "links": null,
                    "created_at": "2023-02-11 21:22:07",
                    "comment_from": "message",
                    "username": "林林",
                    "user_avatar_path": "https://static0.xesimg.com/udc-o-user-avatar/20230527/Talzq9KIOaaUJKTgzzjag4l70w1251.png",
                    "reply_username": "小轩",
                    "emojis": [],
                    "is_like": false,
                    "is_unlike": false,
                    "is_topic_author_like": false,
                    "is_topic_author_reply": false,
                    "can_delete": false,
                    "can_top": false,
                    "user_profile": null
                }
            ]
        },
        "user_profile": null
    },
    {
        "id": 3938809,
        "topic_id": "CP_42018598",
        "parent_id": 0,
        "target_id": 0,
        "user_id": "59842528",
        "reply_user_id": "12907647",
        "content": "6",
        "likes": 0,
        "unlikes": 0,
        "replies": 0,
        "top": 0,
        "removed": 0,
        "links": null,
        "created_at": "2023-02-11 19:44:25",
        "comment_from": "topic",
        "username": "袁梓轩",
        "user_avatar_path": "https://static0.xesimg.com/udc-o-user-avatar/20210221/TalzwVpS8jNrq0uKvMUhVDn-4A1089.png",
        "reply_username": "小轩",
        "emojis": [],
        "is_like": false,
        "is_unlike": false,
        "is_topic_author_like": false,
        "is_topic_author_reply": false,
        "can_delete": false,
        "can_top": false,
        "reply_list": {
            "hasMore": false,
            "total": 0,
            "data": []
        },
        "user_profile": null
    },
    {
        "id": 3938795,
        "topic_id": "CP_42018598",
        "parent_id": 0,
        "target_id": 0,
        "user_id": "59842528",
        "reply_user_id": "12907647",
        "content": "hhh，我一顿上下左右+N疯狂乱点，过关了，正当我还在思考你这游戏的玩法的时候，我的脑子瓦特了",
        "likes": 1,
        "unlikes": 0,
        "replies": 13,
        "top": 0,
        "removed": 0,
        "links": null,
        "created_at": "2023-02-11 19:42:25",
        "comment_from": "topic",
        "username": "袁梓轩",
        "user_avatar_path": "https://static0.xesimg.com/udc-o-user-avatar/20210221/TalzwVpS8jNrq0uKvMUhVDn-4A1089.png",
        "reply_username": "小轩",
        "emojis": [],
        "is_like": false,
        "is_unlike": false,
        "is_topic_author_like": false,
        "is_topic_author_reply": false,
        "can_delete": false,
        "can_top": false,
        "reply_list": {
            "hasMore": true,
            "total": 12,
            "data": [
                {
                    "id": 3938824,
                    "topic_id": "CP_42018598",
                    "parent_id": 3938795,
                    "target_id": 3938795,
                    "user_id": "12907647",
                    "reply_user_id": "59842528",
                    "content": "如果数量少并且没有自动重回起点机制，那么按一个↓，再按很多次→，重复，就能过\n但是后面的关卡会有很多死亡机制，以及长宽高都有几百的大cube（但是有传送门），甚至要你规划最短路，这时候你就绝对不能无脑操作了\n（不过用连点器可以爆刷，但是可能超大cube肯定要操作好一段时间）",
                    "likes": 0,
                    "unlikes": 0,
                    "replies": 0,
                    "top": 0,
                    "removed": 0,
                    "links": null,
                    "created_at": "2023-02-11 19:47:02",
                    "comment_from": "message",
                    "username": "小轩",
                    "user_avatar_path": "https://static1.xesimg.com/udc-o-user-avatar/20240907/TalzonWMSyKikgD5ZEDafJ9YyA_d75edba0b573c72c.png",
                    "reply_username": "袁梓轩",
                    "emojis": [],
                    "is_like": false,
                    "is_unlike": false,
                    "is_topic_author_like": false,
                    "is_topic_author_reply": true,
                    "can_delete": false,
                    "can_top": false,
                    "user_profile": null
                },
                {
                    "id": 3938864,
                    "topic_id": "CP_42018598",
                    "parent_id": 3938795,
                    "target_id": 3938795,
                    "user_id": "12907647",
                    "reply_user_id": "59842528",
                    "content": "有没有发现第二个大地已经很难点了",
                    "likes": 0,
                    "unlikes": 0,
                    "replies": 0,
                    "top": 0,
                    "removed": 0,
                    "links": null,
                    "created_at": "2023-02-11 19:53:09",
                    "comment_from": "topic",
                    "username": "小轩",
                    "user_avatar_path": "https://static1.xesimg.com/udc-o-user-avatar/20240907/TalzonWMSyKikgD5ZEDafJ9YyA_d75edba0b573c72c.png",
                    "reply_username": "袁梓轩",
                    "emojis": [],
                    "is_like": false,
                    "is_unlike": false,
                    "is_topic_author_like": false,
                    "is_topic_author_reply": true,
                    "can_delete": false,
                    "can_top": false,
                    "user_profile": null
                },
                {
                    "id": 3938873,
                    "topic_id": "CP_42018598",
                    "parent_id": 3938795,
                    "target_id": 3938824,
                    "user_id": "2731368",
                    "reply_user_id": "12907647",
                    "content": "为啥我狂按上和右就直接找到一个粉色的块就通过了？",
                    "likes": 0,
                    "unlikes": 0,
                    "replies": 0,
                    "top": 0,
                    "removed": 0,
                    "links": null,
                    "created_at": "2023-02-11 19:54:27",
                    "comment_from": "topic",
                    "username": "林林",
                    "user_avatar_path": "https://static0.xesimg.com/udc-o-user-avatar/20230527/Talzq9KIOaaUJKTgzzjag4l70w1251.png",
                    "reply_username": "小轩",
                    "emojis": [],
                    "is_like": false,
                    "is_unlike": false,
                    "is_topic_author_like": false,
                    "is_topic_author_reply": false,
                    "can_delete": false,
                    "can_top": false,
                    "user_profile": null
                },
                {
                    "id": 3938890,
                    "topic_id": "CP_42018598",
                    "parent_id": 3938795,
                    "target_id": 3938873,
                    "user_id": "12907647",
                    "reply_user_id": "2731368",
                    "content": "地图较小，每次↗都会导致一定的维度轴旋转或者平移，同时玩家方向改变，在小地图中经常能很幸运",
                    "likes": 0,
                    "unlikes": 0,
                    "replies": 0,
                    "top": 0,
                    "removed": 0,
                    "links": null,
                    "created_at": "2023-02-11 19:57:11",
                    "comment_from": "message",
                    "username": "小轩",
                    "user_avatar_path": "https://static1.xesimg.com/udc-o-user-avatar/20240907/TalzonWMSyKikgD5ZEDafJ9YyA_d75edba0b573c72c.png",
                    "reply_username": "林林",
                    "emojis": [],
                    "is_like": false,
                    "is_unlike": false,
                    "is_topic_author_like": false,
                    "is_topic_author_reply": true,
                    "can_delete": false,
                    "can_top": false,
                    "user_profile": null
                },
                {
                    "id": 3938906,
                    "topic_id": "CP_42018598",
                    "parent_id": 3938795,
                    "target_id": 3938890,
                    "user_id": "2731368",
                    "reply_user_id": "12907647",
                    "content": "我是同时按的。。。就是说在地图对角线上我找到了那个通关块？",
                    "likes": 0,
                    "unlikes": 0,
                    "replies": 0,
                    "top": 0,
                    "removed": 0,
                    "links": null,
                    "created_at": "2023-02-11 20:01:20",
                    "comment_from": "message",
                    "username": "林林",
                    "user_avatar_path": "https://static0.xesimg.com/udc-o-user-avatar/20230527/Talzq9KIOaaUJKTgzzjag4l70w1251.png",
                    "reply_username": "小轩",
                    "emojis": [],
                    "is_like": false,
                    "is_unlike": false,
                    "is_topic_author_like": false,
                    "is_topic_author_reply": false,
                    "can_delete": false,
                    "can_top": false,
                    "user_profile": null
                },
                {
                    "id": 3939166,
                    "topic_id": "CP_42018598",
                    "parent_id": 3938795,
                    "target_id": 3939162,
                    "user_id": "2731368",
                    "reply_user_id": "12907647",
                    "content": "呃",
                    "likes": 0,
                    "unlikes": 0,
                    "replies": 0,
                    "top": 0,
                    "removed": 0,
                    "links": null,
                    "created_at": "2023-02-11 20:45:27",
                    "comment_from": "message",
                    "username": "林林",
                    "user_avatar_path": "https://static0.xesimg.com/udc-o-user-avatar/20230527/Talzq9KIOaaUJKTgzzjag4l70w1251.png",
                    "reply_username": "小轩",
                    "emojis": [],
                    "is_like": false,
                    "is_unlike": false,
                    "is_topic_author_like": false,
                    "is_topic_author_reply": false,
                    "can_delete": false,
                    "can_top": false,
                    "user_profile": null
                },
                {
                    "id": 3939168,
                    "topic_id": "CP_42018598",
                    "parent_id": 3938795,
                    "target_id": 3939166,
                    "user_id": "12907647",
                    "reply_user_id": "2731368",
                    "content": "你看了我就删了",
                    "likes": 0,
                    "unlikes": 0,
                    "replies": 0,
                    "top": 0,
                    "removed": 0,
                    "links": null,
                    "created_at": "2023-02-11 20:46:04",
                    "comment_from": "topic",
                    "username": "小轩",
                    "user_avatar_path": "https://static1.xesimg.com/udc-o-user-avatar/20240907/TalzonWMSyKikgD5ZEDafJ9YyA_d75edba0b573c72c.png",
                    "reply_username": "林林",
                    "emojis": [],
                    "is_like": false,
                    "is_unlike": false,
                    "is_topic_author_like": false,
                    "is_topic_author_reply": true,
                    "can_delete": false,
                    "can_top": false,
                    "user_profile": null
                },
                {
                    "id": 3939169,
                    "topic_id": "CP_42018598",
                    "parent_id": 3938795,
                    "target_id": 3939168,
                    "user_id": "2731368",
                    "reply_user_id": "12907647",
                    "content": "不对啊，pygame会遍历所有同时发生的事件",
                    "likes": 0,
                    "unlikes": 0,
                    "replies": 0,
                    "top": 0,
                    "removed": 0,
                    "links": null,
                    "created_at": "2023-02-11 20:46:23",
                    "comment_from": "message",
                    "username": "林林",
                    "user_avatar_path": "https://static0.xesimg.com/udc-o-user-avatar/20230527/Talzq9KIOaaUJKTgzzjag4l70w1251.png",
                    "reply_username": "小轩",
                    "emojis": [],
                    "is_like": false,
                    "is_unlike": false,
                    "is_topic_author_like": false,
                    "is_topic_author_reply": false,
                    "can_delete": false,
                    "can_top": false,
                    "user_profile": null
                },
                {
                    "id": 3939177,
                    "topic_id": "CP_42018598",
                    "parent_id": 3938795,
                    "target_id": 3939169,
                    "user_id": "12907647",
                    "reply_user_id": "2731368",
                    "content": "我用的是if-elif-else而不是if if if if if if...，使其同时发生时只判断后者",
                    "likes": 0,
                    "unlikes": 0,
                    "replies": 0,
                    "top": 0,
                    "removed": 0,
                    "links": null,
                    "created_at": "2023-02-11 20:47:31",
                    "comment_from": "message",
                    "username": "小轩",
                    "user_avatar_path": "https://static1.xesimg.com/udc-o-user-avatar/20240907/TalzonWMSyKikgD5ZEDafJ9YyA_d75edba0b573c72c.png",
                    "reply_username": "林林",
                    "emojis": [],
                    "is_like": false,
                    "is_unlike": false,
                    "is_topic_author_like": false,
                    "is_topic_author_reply": true,
                    "can_delete": false,
                    "can_top": false,
                    "user_profile": null
                },
                {
                    "id": 3939184,
                    "topic_id": "CP_42018598",
                    "parent_id": 3938795,
                    "target_id": 3939169,
                    "user_id": "12907647",
                    "reply_user_id": "2731368",
                    "content": "判断前者，说错了",
                    "likes": 0,
                    "unlikes": 0,
                    "replies": 0,
                    "top": 0,
                    "removed": 0,
                    "links": null,
                    "created_at": "2023-02-11 20:48:02",
                    "comment_from": "message",
                    "username": "小轩",
                    "user_avatar_path": "https://static1.xesimg.com/udc-o-user-avatar/20240907/TalzonWMSyKikgD5ZEDafJ9YyA_d75edba0b573c72c.png",
                    "reply_username": "林林",
                    "emojis": [],
                    "is_like": false,
                    "is_unlike": false,
                    "is_topic_author_like": false,
                    "is_topic_author_reply": true,
                    "can_delete": false,
                    "can_top": false,
                    "user_profile": null
                },
                {
                    "id": 3939191,
                    "topic_id": "CP_42018598",
                    "parent_id": 3938795,
                    "target_id": 3939177,
                    "user_id": "2731368",
                    "reply_user_id": "12907647",
                    "content": "az（我记得pygame的事件是会被for遍历的，一般的程序结构都这样）",
                    "likes": 0,
                    "unlikes": 0,
                    "replies": 0,
                    "top": 0,
                    "removed": 0,
                    "links": null,
                    "created_at": "2023-02-11 20:49:09",
                    "comment_from": "message",
                    "username": "林林",
                    "user_avatar_path": "https://static0.xesimg.com/udc-o-user-avatar/20230527/Talzq9KIOaaUJKTgzzjag4l70w1251.png",
                    "reply_username": "小轩",
                    "emojis": [],
                    "is_like": false,
                    "is_unlike": false,
                    "is_topic_author_like": false,
                    "is_topic_author_reply": false,
                    "can_delete": false,
                    "can_top": false,
                    "user_profile": null
                },
                {
                    "id": 3939210,
                    "topic_id": "CP_42018598",
                    "parent_id": 3938795,
                    "target_id": 3939191,
                    "user_id": "12907647",
                    "reply_user_id": "2731368",
                    "content": "是的，但是如果同时发生快过电脑反应那么栈就会被先压一截",
                    "likes": 0,
                    "unlikes": 0,
                    "replies": 0,
                    "top": 0,
                    "removed": 0,
                    "links": null,
                    "created_at": "2023-02-11 20:51:05",
                    "comment_from": "message",
                    "username": "小轩",
                    "user_avatar_path": "https://static1.xesimg.com/udc-o-user-avatar/20240907/TalzonWMSyKikgD5ZEDafJ9YyA_d75edba0b573c72c.png",
                    "reply_username": "林林",
                    "emojis": [],
                    "is_like": false,
                    "is_unlike": false,
                    "is_topic_author_like": false,
                    "is_topic_author_reply": true,
                    "can_delete": false,
                    "can_top": false,
                    "user_profile": null
                }
            ]
        },
        "user_profile": null
    },
    {
        "id": 3938791,
        "topic_id": "CP_42018598",
        "parent_id": 0,
        "target_id": 0,
        "user_id": "17025146",
        "reply_user_id": "12907647",
        "content": "《我不一定能玩懂游戏，但我一定能看懂代码》",
        "likes": 1,
        "unlikes": 0,
        "replies": 15,
        "top": 0,
        "removed": 0,
        "links": null,
        "created_at": "2023-02-11 19:41:17",
        "comment_from": "topic",
        "username": "吴宇航",
        "user_avatar_path": "https://static0.xesimg.com/udc-o-user-avatar/20210418/Talz4LBDwc2k3lqGS74fz6CFrg1516.gif",
        "reply_username": "小轩",
        "emojis": [],
        "is_like": false,
        "is_unlike": false,
        "is_topic_author_like": false,
        "is_topic_author_reply": false,
        "can_delete": false,
        "can_top": false,
        "reply_list": {
            "hasMore": true,
            "total": 15,
            "data": [
                {
                    "id": 3938793,
                    "topic_id": "CP_42018598",
                    "parent_id": 3938791,
                    "target_id": 3938791,
                    "user_id": "12907647",
                    "reply_user_id": "17025146",
                    "content": "不要看，看了就什么都剧透了！",
                    "likes": 0,
                    "unlikes": 0,
                    "replies": 0,
                    "top": 0,
                    "removed": 0,
                    "links": null,
                    "created_at": "2023-02-11 19:41:55",
                    "comment_from": "topic",
                    "username": "小轩",
                    "user_avatar_path": "https://static1.xesimg.com/udc-o-user-avatar/20240907/TalzonWMSyKikgD5ZEDafJ9YyA_d75edba0b573c72c.png",
                    "reply_username": "吴宇航",
                    "emojis": [],
                    "is_like": false,
                    "is_unlike": false,
                    "is_topic_author_like": false,
                    "is_topic_author_reply": true,
                    "can_delete": false,
                    "can_top": false,
                    "user_profile": null
                },
                {
                    "id": 3938797,
                    "topic_id": "CP_42018598",
                    "parent_id": 3938791,
                    "target_id": 3938791,
                    "user_id": "59842528",
                    "reply_user_id": "17025146",
                    "content": "《我看不懂，但大受震撼》",
                    "likes": 0,
                    "unlikes": 0,
                    "replies": 0,
                    "top": 0,
                    "removed": 0,
                    "links": null,
                    "created_at": "2023-02-11 19:42:56",
                    "comment_from": "topic",
                    "username": "袁梓轩",
                    "user_avatar_path": "https://static0.xesimg.com/udc-o-user-avatar/20210221/TalzwVpS8jNrq0uKvMUhVDn-4A1089.png",
                    "reply_username": "吴宇航",
                    "emojis": [],
                    "is_like": false,
                    "is_unlike": false,
                    "is_topic_author_like": false,
                    "is_topic_author_reply": false,
                    "can_delete": false,
                    "can_top": false,
                    "user_profile": null
                },
                {
                    "id": 3938801,
                    "topic_id": "CP_42018598",
                    "parent_id": 3938791,
                    "target_id": 3938793,
                    "user_id": "17025146",
                    "reply_user_id": "12907647",
                    "content": "、、、我对游戏也不感兴趣啊，只对算法感兴趣",
                    "likes": 0,
                    "unlikes": 0,
                    "replies": 0,
                    "top": 0,
                    "removed": 0,
                    "links": null,
                    "created_at": "2023-02-11 19:43:10",
                    "comment_from": "message",
                    "username": "吴宇航",
                    "user_avatar_path": "https://static0.xesimg.com/udc-o-user-avatar/20210418/Talz4LBDwc2k3lqGS74fz6CFrg1516.gif",
                    "reply_username": "小轩",
                    "emojis": [],
                    "is_like": false,
                    "is_unlike": false,
                    "is_topic_author_like": false,
                    "is_topic_author_reply": false,
                    "can_delete": false,
                    "can_top": false,
                    "user_profile": null
                },
                {
                    "id": 3938832,
                    "topic_id": "CP_42018598",
                    "parent_id": 3938791,
                    "target_id": 3938801,
                    "user_id": "12907647",
                    "reply_user_id": "17025146",
                    "content": "有时候玩游戏还比写算法难",
                    "likes": 0,
                    "unlikes": 0,
                    "replies": 0,
                    "top": 0,
                    "removed": 0,
                    "links": null,
                    "created_at": "2023-02-11 19:49:00",
                    "comment_from": "message",
                    "username": "小轩",
                    "user_avatar_path": "https://static1.xesimg.com/udc-o-user-avatar/20240907/TalzonWMSyKikgD5ZEDafJ9YyA_d75edba0b573c72c.png",
                    "reply_username": "吴宇航",
                    "emojis": [],
                    "is_like": false,
                    "is_unlike": false,
                    "is_topic_author_like": false,
                    "is_topic_author_reply": true,
                    "can_delete": false,
                    "can_top": false,
                    "user_profile": null
                },
                {
                    "id": 3938855,
                    "topic_id": "CP_42018598",
                    "parent_id": 3938791,
                    "target_id": 3938832,
                    "user_id": "17025146",
                    "reply_user_id": "12907647",
                    "content": "所以我不一定能直接玩懂游戏，但我能看懂算法，那就一定能操纵游戏（",
                    "likes": 0,
                    "unlikes": 0,
                    "replies": 0,
                    "top": 0,
                    "removed": 0,
                    "links": null,
                    "created_at": "2023-02-11 19:52:16",
                    "comment_from": "message",
                    "username": "吴宇航",
                    "user_avatar_path": "https://static0.xesimg.com/udc-o-user-avatar/20210418/Talz4LBDwc2k3lqGS74fz6CFrg1516.gif",
                    "reply_username": "小轩",
                    "emojis": [],
                    "is_like": false,
                    "is_unlike": false,
                    "is_topic_author_like": false,
                    "is_topic_author_reply": false,
                    "can_delete": false,
                    "can_top": false,
                    "user_profile": null
                },
                {
                    "id": 3938895,
                    "topic_id": "CP_42018598",
                    "parent_id": 3938791,
                    "target_id": 3938855,
                    "user_id": "12907647",
                    "reply_user_id": "17025146",
                    "content": "不一定，你可能读完知道它怎么工作但是也不知道怎么回事",
                    "likes": 0,
                    "unlikes": 0,
                    "replies": 0,
                    "top": 0,
                    "removed": 0,
                    "links": null,
                    "created_at": "2023-02-11 19:57:50",
                    "comment_from": "message",
                    "username": "小轩",
                    "user_avatar_path": "https://static1.xesimg.com/udc-o-user-avatar/20240907/TalzonWMSyKikgD5ZEDafJ9YyA_d75edba0b573c72c.png",
                    "reply_username": "吴宇航",
                    "emojis": [],
                    "is_like": false,
                    "is_unlike": false,
                    "is_topic_author_like": false,
                    "is_topic_author_reply": true,
                    "can_delete": false,
                    "can_top": false,
                    "user_profile": null
                },
                {
                    "id": 3938898,
                    "topic_id": "CP_42018598",
                    "parent_id": 3938791,
                    "target_id": 3938895,
                    "user_id": "17025146",
                    "reply_user_id": "12907647",
                    "content": "只要从代码中提取出通关的条件，然后将条件中的变量带入到代码整体中，就可以将变量还原为操作",
                    "likes": 0,
                    "unlikes": 0,
                    "replies": 0,
                    "top": 0,
                    "removed": 0,
                    "links": null,
                    "created_at": "2023-02-11 19:58:50",
                    "comment_from": "message",
                    "username": "吴宇航",
                    "user_avatar_path": "https://static0.xesimg.com/udc-o-user-avatar/20210418/Talz4LBDwc2k3lqGS74fz6CFrg1516.gif",
                    "reply_username": "小轩",
                    "emojis": [],
                    "is_like": false,
                    "is_unlike": false,
                    "is_topic_author_like": false,
                    "is_topic_author_reply": false,
                    "can_delete": false,
                    "can_top": false,
                    "user_profile": null
                },
                {
                    "id": 3939068,
                    "topic_id": "CP_42018598",
                    "parent_id": 3938791,
                    "target_id": 3938898,
                    "user_id": "12907647",
                    "reply_user_id": "17025146",
                    "content": "直接通关也太耍赖了\n我洛谷在学计算C(m)(n)",
                    "likes": 0,
                    "unlikes": 0,
                    "replies": 0,
                    "top": 0,
                    "removed": 0,
                    "links": null,
                    "created_at": "2023-02-11 20:29:55",
                    "comment_from": "message",
                    "username": "小轩",
                    "user_avatar_path": "https://static1.xesimg.com/udc-o-user-avatar/20240907/TalzonWMSyKikgD5ZEDafJ9YyA_d75edba0b573c72c.png",
                    "reply_username": "吴宇航",
                    "emojis": [],
                    "is_like": false,
                    "is_unlike": false,
                    "is_topic_author_like": false,
                    "is_topic_author_reply": true,
                    "can_delete": false,
                    "can_top": false,
                    "user_profile": null
                },
                {
                    "id": 3939131,
                    "topic_id": "CP_42018598",
                    "parent_id": 3938791,
                    "target_id": 3939068,
                    "user_id": "17025146",
                    "reply_user_id": "12907647",
                    "content": "也许游戏制作者让游戏难到不让人通关会更耍赖一些（",
                    "likes": 0,
                    "unlikes": 0,
                    "replies": 0,
                    "top": 0,
                    "removed": 0,
                    "links": null,
                    "created_at": "2023-02-11 20:40:56",
                    "comment_from": "message",
                    "username": "吴宇航",
                    "user_avatar_path": "https://static0.xesimg.com/udc-o-user-avatar/20210418/Talz4LBDwc2k3lqGS74fz6CFrg1516.gif",
                    "reply_username": "小轩",
                    "emojis": [],
                    "is_like": false,
                    "is_unlike": false,
                    "is_topic_author_like": false,
                    "is_topic_author_reply": false,
                    "can_delete": false,
                    "can_top": false,
                    "user_profile": null
                },
                {
                    "id": 3939171,
                    "topic_id": "CP_42018598",
                    "parent_id": 3938791,
                    "target_id": 3939131,
                    "user_id": "12907647",
                    "reply_user_id": "17025146",
                    "content": "其实不是特别难，如果你聪明的话",
                    "likes": 0,
                    "unlikes": 0,
                    "replies": 0,
                    "top": 0,
                    "removed": 0,
                    "links": null,
                    "created_at": "2023-02-11 20:46:43",
                    "comment_from": "message",
                    "username": "小轩",
                    "user_avatar_path": "https://static1.xesimg.com/udc-o-user-avatar/20240907/TalzonWMSyKikgD5ZEDafJ9YyA_d75edba0b573c72c.png",
                    "reply_username": "吴宇航",
                    "emojis": [],
                    "is_like": false,
                    "is_unlike": false,
                    "is_topic_author_like": false,
                    "is_topic_author_reply": true,
                    "can_delete": false,
                    "can_top": false,
                    "user_profile": null
                },
                {
                    "id": 3939179,
                    "topic_id": "CP_42018598",
                    "parent_id": 3938791,
                    "target_id": 3939171,
                    "user_id": "17025146",
                    "reply_user_id": "12907647",
                    "content": "游戏从来都是面向大众的，毕竟聪明人只是少数",
                    "likes": 0,
                    "unlikes": 0,
                    "replies": 0,
                    "top": 0,
                    "removed": 0,
                    "links": null,
                    "created_at": "2023-02-11 20:47:41",
                    "comment_from": "message",
                    "username": "吴宇航",
                    "user_avatar_path": "https://static0.xesimg.com/udc-o-user-avatar/20210418/Talz4LBDwc2k3lqGS74fz6CFrg1516.gif",
                    "reply_username": "小轩",
                    "emojis": [],
                    "is_like": false,
                    "is_unlike": false,
                    "is_topic_author_like": false,
                    "is_topic_author_reply": false,
                    "can_delete": false,
                    "can_top": false,
                    "user_profile": null
                },
                {
                    "id": 3939193,
                    "topic_id": "CP_42018598",
                    "parent_id": 3938791,
                    "target_id": 3939179,
                    "user_id": "12907647",
                    "reply_user_id": "17025146",
                    "content": "也有很多游戏就是因为难才好玩的，专门屏蔽了低智商人，所以我还只发在编程社区等，这些地方的人智商较高。你看steam上也有很多智商门槛很高的游戏的",
                    "likes": 0,
                    "unlikes": 0,
                    "replies": 0,
                    "top": 0,
                    "removed": 0,
                    "links": null,
                    "created_at": "2023-02-11 20:49:28",
                    "comment_from": "message",
                    "username": "小轩",
                    "user_avatar_path": "https://static1.xesimg.com/udc-o-user-avatar/20240907/TalzonWMSyKikgD5ZEDafJ9YyA_d75edba0b573c72c.png",
                    "reply_username": "吴宇航",
                    "emojis": [],
                    "is_like": false,
                    "is_unlike": false,
                    "is_topic_author_like": false,
                    "is_topic_author_reply": true,
                    "can_delete": false,
                    "can_top": false,
                    "user_profile": null
                },
                {
                    "id": 3939204,
                    "topic_id": "CP_42018598",
                    "parent_id": 3938791,
                    "target_id": 3939179,
                    "user_id": "12907647",
                    "reply_user_id": "17025146",
                    "content": "《关于我创作了这个东西超越了游玩者一大截这件事》",
                    "likes": 0,
                    "unlikes": 0,
                    "replies": 0,
                    "top": 0,
                    "removed": 0,
                    "links": null,
                    "created_at": "2023-02-11 20:50:20",
                    "comment_from": "message",
                    "username": "小轩",
                    "user_avatar_path": "https://static1.xesimg.com/udc-o-user-avatar/20240907/TalzonWMSyKikgD5ZEDafJ9YyA_d75edba0b573c72c.png",
                    "reply_username": "吴宇航",
                    "emojis": [],
                    "is_like": false,
                    "is_unlike": false,
                    "is_topic_author_like": false,
                    "is_topic_author_reply": true,
                    "can_delete": false,
                    "can_top": false,
                    "user_profile": null
                },
                {
                    "id": 3939212,
                    "topic_id": "CP_42018598",
                    "parent_id": 3938791,
                    "target_id": 3939193,
                    "user_id": "17025146",
                    "reply_user_id": "12907647",
                    "content": "但是我几乎都不玩游戏，因为作为一名coder，我看的太透彻了，就没乐趣了。。。",
                    "likes": 0,
                    "unlikes": 0,
                    "replies": 0,
                    "top": 0,
                    "removed": 0,
                    "links": null,
                    "created_at": "2023-02-11 20:51:32",
                    "comment_from": "message",
                    "username": "吴宇航",
                    "user_avatar_path": "https://static0.xesimg.com/udc-o-user-avatar/20210418/Talz4LBDwc2k3lqGS74fz6CFrg1516.gif",
                    "reply_username": "小轩",
                    "emojis": [],
                    "is_like": false,
                    "is_unlike": false,
                    "is_topic_author_like": false,
                    "is_topic_author_reply": false,
                    "can_delete": false,
                    "can_top": false,
                    "user_profile": null
                },
                {
                    "id": 3939286,
                    "topic_id": "CP_42018598",
                    "parent_id": 3938791,
                    "target_id": 3939212,
                    "user_id": "12907647",
                    "reply_user_id": "17025146",
                    "content": "。。。",
                    "likes": 0,
                    "unlikes": 0,
                    "replies": 0,
                    "top": 0,
                    "removed": 0,
                    "links": null,
                    "created_at": "2023-02-11 21:06:51",
                    "comment_from": "message",
                    "username": "小轩",
                    "user_avatar_path": "https://static1.xesimg.com/udc-o-user-avatar/20240907/TalzonWMSyKikgD5ZEDafJ9YyA_d75edba0b573c72c.png",
                    "reply_username": "吴宇航",
                    "emojis": [],
                    "is_like": false,
                    "is_unlike": false,
                    "is_topic_author_like": false,
                    "is_topic_author_reply": true,
                    "can_delete": false,
                    "can_top": false,
                    "user_profile": null
                }
            ]
        },
        "user_profile": null
    },
    {
        "id": 3938736,
        "topic_id": "CP_42018598",
        "parent_id": 0,
        "target_id": 0,
        "user_id": "10583579",
        "reply_user_id": "12907647",
        "content": "6",
        "likes": 0,
        "unlikes": 0,
        "replies": 0,
        "top": 0,
        "removed": 0,
        "links": null,
        "created_at": "2023-02-11 19:34:17",
        "comment_from": "topic",
        "username": "何嘉晨",
        "user_avatar_path": "https://img.100tal.com/user/20200730/Tall4HQqhG5rGNwFPlaLrVUxWA1748.png",
        "reply_username": "小轩",
        "emojis": [],
        "is_like": false,
        "is_unlike": false,
        "is_topic_author_like": false,
        "is_topic_author_reply": false,
        "can_delete": false,
        "can_top": false,
        "reply_list": {
            "hasMore": false,
            "total": 0,
            "data": []
        },
        "user_profile": null
    },
    {
        "id": 3938730,
        "topic_id": "CP_42018598",
        "parent_id": 0,
        "target_id": 0,
        "user_id": "17025146",
        "reply_user_id": "12907647",
        "content": "666",
        "likes": 0,
        "unlikes": 0,
        "replies": 0,
        "top": 0,
        "removed": 0,
        "links": null,
        "created_at": "2023-02-11 19:33:48",
        "comment_from": "topic",
        "username": "吴宇航",
        "user_avatar_path": "https://static0.xesimg.com/udc-o-user-avatar/20210418/Talz4LBDwc2k3lqGS74fz6CFrg1516.gif",
        "reply_username": "小轩",
        "emojis": [],
        "is_like": false,
        "is_unlike": false,
        "is_topic_author_like": false,
        "is_topic_author_reply": false,
        "can_delete": false,
        "can_top": false,
        "reply_list": {
            "hasMore": false,
            "total": 0,
            "data": []
        },
        "user_profile": null
    }
]