[
    {
        "id": 3160451,
        "topic_id": "CP_36570809",
        "parent_id": 0,
        "target_id": 0,
        "user_id": "10583579",
        "reply_user_id": "17025146",
        "content": "那个实例是不是这样的\nhttps://livefile.xesimg.com/programme/python_assets/dbc68d849dbdbbc0c86b6d14534379a1.png",
        "likes": 0,
        "unlikes": 0,
        "replies": 10,
        "top": 0,
        "removed": 0,
        "links": null,
        "created_at": "2022-08-08 18:02:05",
        "comment_from": "topic",
        "username": "何嘉晨",
        "user_avatar_path": "https://img.100tal.com/user/20200730/Tall4HQqhG5rGNwFPlaLrVUxWA1748.png",
        "reply_username": "吴宇航",
        "emojis": [],
        "is_like": false,
        "is_unlike": false,
        "is_topic_author_like": false,
        "is_topic_author_reply": false,
        "can_delete": false,
        "can_top": false,
        "reply_list": {
            "hasMore": true,
            "total": 10,
            "data": [
                {
                    "id": 3160457,
                    "topic_id": "CP_36570809",
                    "parent_id": 3160451,
                    "target_id": 3160451,
                    "user_id": "17025146",
                    "reply_user_id": "10583579",
                    "content": "哪一个？就是之前那个算法出错的那个示例？就是的",
                    "likes": 0,
                    "unlikes": 0,
                    "replies": 0,
                    "top": 0,
                    "removed": 0,
                    "links": null,
                    "created_at": "2022-08-08 18:03:04",
                    "comment_from": "message",
                    "username": "吴宇航",
                    "user_avatar_path": "https://static0.xesimg.com/udc-o-user-avatar/20210418/Talz4LBDwc2k3lqGS74fz6CFrg1516.gif",
                    "reply_username": "何嘉晨",
                    "emojis": [],
                    "is_like": false,
                    "is_unlike": false,
                    "is_topic_author_like": false,
                    "is_topic_author_reply": true,
                    "can_delete": false,
                    "can_top": false,
                    "user_profile": null
                },
                {
                    "id": 3160464,
                    "topic_id": "CP_36570809",
                    "parent_id": 3160451,
                    "target_id": 3160457,
                    "user_id": "10583579",
                    "reply_user_id": "17025146",
                    "content": "对，我想了半天，后来发现是这个问题，特意搞了个图",
                    "likes": 0,
                    "unlikes": 0,
                    "replies": 0,
                    "top": 0,
                    "removed": 0,
                    "links": null,
                    "created_at": "2022-08-08 18:04:11",
                    "comment_from": "message",
                    "username": "何嘉晨",
                    "user_avatar_path": "https://img.100tal.com/user/20200730/Tall4HQqhG5rGNwFPlaLrVUxWA1748.png",
                    "reply_username": "吴宇航",
                    "emojis": [],
                    "is_like": false,
                    "is_unlike": false,
                    "is_topic_author_like": false,
                    "is_topic_author_reply": false,
                    "can_delete": false,
                    "can_top": false,
                    "user_profile": null
                },
                {
                    "id": 3160469,
                    "topic_id": "CP_36570809",
                    "parent_id": 3160451,
                    "target_id": 3160464,
                    "user_id": "17025146",
                    "reply_user_id": "10583579",
                    "content": "没错，现在终于解决了",
                    "likes": 0,
                    "unlikes": 0,
                    "replies": 0,
                    "top": 0,
                    "removed": 0,
                    "links": null,
                    "created_at": "2022-08-08 18:04:54",
                    "comment_from": "message",
                    "username": "吴宇航",
                    "user_avatar_path": "https://static0.xesimg.com/udc-o-user-avatar/20210418/Talz4LBDwc2k3lqGS74fz6CFrg1516.gif",
                    "reply_username": "何嘉晨",
                    "emojis": [],
                    "is_like": false,
                    "is_unlike": false,
                    "is_topic_author_like": false,
                    "is_topic_author_reply": true,
                    "can_delete": false,
                    "can_top": false,
                    "user_profile": null
                },
                {
                    "id": 3160476,
                    "topic_id": "CP_36570809",
                    "parent_id": 3160451,
                    "target_id": 3160469,
                    "user_id": "10583579",
                    "reply_user_id": "17025146",
                    "content": "框架出来了，我先把这些搞上去",
                    "likes": 0,
                    "unlikes": 0,
                    "replies": 0,
                    "top": 0,
                    "removed": 0,
                    "links": null,
                    "created_at": "2022-08-08 18:05:23",
                    "comment_from": "message",
                    "username": "何嘉晨",
                    "user_avatar_path": "https://img.100tal.com/user/20200730/Tall4HQqhG5rGNwFPlaLrVUxWA1748.png",
                    "reply_username": "吴宇航",
                    "emojis": [],
                    "is_like": false,
                    "is_unlike": false,
                    "is_topic_author_like": false,
                    "is_topic_author_reply": false,
                    "can_delete": false,
                    "can_top": false,
                    "user_profile": null
                },
                {
                    "id": 3160487,
                    "topic_id": "CP_36570809",
                    "parent_id": 3160451,
                    "target_id": 3160476,
                    "user_id": "17025146",
                    "reply_user_id": "10583579",
                    "content": "OK，不过除了这四种遍历，二叉树应该还要有插入和删除节点的算法吧",
                    "likes": 0,
                    "unlikes": 0,
                    "replies": 0,
                    "top": 0,
                    "removed": 0,
                    "links": null,
                    "created_at": "2022-08-08 18:06:34",
                    "comment_from": "message",
                    "username": "吴宇航",
                    "user_avatar_path": "https://static0.xesimg.com/udc-o-user-avatar/20210418/Talz4LBDwc2k3lqGS74fz6CFrg1516.gif",
                    "reply_username": "何嘉晨",
                    "emojis": [],
                    "is_like": false,
                    "is_unlike": false,
                    "is_topic_author_like": false,
                    "is_topic_author_reply": true,
                    "can_delete": false,
                    "can_top": false,
                    "user_profile": null
                },
                {
                    "id": 3160503,
                    "topic_id": "CP_36570809",
                    "parent_id": 3160451,
                    "target_id": 3160487,
                    "user_id": "10583579",
                    "reply_user_id": "17025146",
                    "content": "雀食，我的链表这块也没做，我准备搞个new_struct库",
                    "likes": 0,
                    "unlikes": 0,
                    "replies": 0,
                    "top": 0,
                    "removed": 0,
                    "links": null,
                    "created_at": "2022-08-08 18:09:41",
                    "comment_from": "message",
                    "username": "何嘉晨",
                    "user_avatar_path": "https://img.100tal.com/user/20200730/Tall4HQqhG5rGNwFPlaLrVUxWA1748.png",
                    "reply_username": "吴宇航",
                    "emojis": [],
                    "is_like": false,
                    "is_unlike": false,
                    "is_topic_author_like": false,
                    "is_topic_author_reply": false,
                    "can_delete": false,
                    "can_top": false,
                    "user_profile": null
                },
                {
                    "id": 3160516,
                    "topic_id": "CP_36570809",
                    "parent_id": 3160451,
                    "target_id": 3160503,
                    "user_id": "17025146",
                    "reply_user_id": "10583579",
                    "content": "我觉得可行，在new_struct里面就可以实现大多数常见的数据结构，如：堆、栈、队列、二叉树、红黑树、链表等等等等",
                    "likes": 0,
                    "unlikes": 0,
                    "replies": 0,
                    "top": 0,
                    "removed": 0,
                    "links": null,
                    "created_at": "2022-08-08 18:12:17",
                    "comment_from": "message",
                    "username": "吴宇航",
                    "user_avatar_path": "https://static0.xesimg.com/udc-o-user-avatar/20210418/Talz4LBDwc2k3lqGS74fz6CFrg1516.gif",
                    "reply_username": "何嘉晨",
                    "emojis": [],
                    "is_like": false,
                    "is_unlike": false,
                    "is_topic_author_like": false,
                    "is_topic_author_reply": true,
                    "can_delete": false,
                    "can_top": false,
                    "user_profile": null
                },
                {
                    "id": 3160535,
                    "topic_id": "CP_36570809",
                    "parent_id": 3160451,
                    "target_id": 3160503,
                    "user_id": "17025146",
                    "reply_user_id": "10583579",
                    "content": "然额这个任务太艰巨了，不说别的，就是一个红黑树都能让我们写吐血，更别提还有2-3-4树什么的了",
                    "likes": 0,
                    "unlikes": 0,
                    "replies": 0,
                    "top": 0,
                    "removed": 0,
                    "links": null,
                    "created_at": "2022-08-08 18:17:44",
                    "comment_from": "message",
                    "username": "吴宇航",
                    "user_avatar_path": "https://static0.xesimg.com/udc-o-user-avatar/20210418/Talz4LBDwc2k3lqGS74fz6CFrg1516.gif",
                    "reply_username": "何嘉晨",
                    "emojis": [],
                    "is_like": false,
                    "is_unlike": false,
                    "is_topic_author_like": false,
                    "is_topic_author_reply": true,
                    "can_delete": false,
                    "can_top": false,
                    "user_profile": null
                },
                {
                    "id": 3160579,
                    "topic_id": "CP_36570809",
                    "parent_id": 3160451,
                    "target_id": 3160535,
                    "user_id": "10583579",
                    "reply_user_id": "17025146",
                    "content": "别搞红黑树了",
                    "likes": 0,
                    "unlikes": 0,
                    "replies": 0,
                    "top": 0,
                    "removed": 0,
                    "links": null,
                    "created_at": "2022-08-08 18:28:39",
                    "comment_from": "message",
                    "username": "何嘉晨",
                    "user_avatar_path": "https://img.100tal.com/user/20200730/Tall4HQqhG5rGNwFPlaLrVUxWA1748.png",
                    "reply_username": "吴宇航",
                    "emojis": [],
                    "is_like": false,
                    "is_unlike": false,
                    "is_topic_author_like": false,
                    "is_topic_author_reply": false,
                    "can_delete": false,
                    "can_top": false,
                    "user_profile": null
                },
                {
                    "id": 3160681,
                    "topic_id": "CP_36570809",
                    "parent_id": 3160451,
                    "target_id": 3160579,
                    "user_id": "17025146",
                    "reply_user_id": "10583579",
                    "content": "也对，这玩 意儿写起来不知道有多烦",
                    "likes": 0,
                    "unlikes": 0,
                    "replies": 0,
                    "top": 0,
                    "removed": 0,
                    "links": null,
                    "created_at": "2022-08-08 18:45:37",
                    "comment_from": "message",
                    "username": "吴宇航",
                    "user_avatar_path": "https://static0.xesimg.com/udc-o-user-avatar/20210418/Talz4LBDwc2k3lqGS74fz6CFrg1516.gif",
                    "reply_username": "何嘉晨",
                    "emojis": [],
                    "is_like": false,
                    "is_unlike": false,
                    "is_topic_author_like": false,
                    "is_topic_author_reply": true,
                    "can_delete": false,
                    "can_top": false,
                    "user_profile": null
                }
            ]
        },
        "user_profile": null
    }
]